baostock/__init__.py
baostock/common/__init__.py
baostock/common/contants.py
baostock/common/context.py
baostock/corpreport/__init__.py
baostock/corpreport/corp_performance.py
baostock/data/__init__.py
baostock/data/messageheader.py
baostock/data/msg.py
baostock/data/resultset.py
baostock/evaluation/__init__.py
baostock/evaluation/season_index.py
baostock/login/__init__.py
baostock/login/loginout.py
baostock/metadata/__init__.py
baostock/metadata/stock_metadata.py
baostock/realtime/__init__.py
baostock/realtime/subscibe.py
baostock/security/__init__.py
baostock/security/history.py
baostock/util/__init__.py
baostock/util/socketutil.py
baostock/util/stringutil.py
baostock-0.7.5.dist-info/DESCRIPTION.rst
baostock-0.7.5.dist-info/METADATA
baostock-0.7.5.dist-info/RECORD
baostock-0.7.5.dist-info/WHEEL
baostock-0.7.5.dist-info/metadata.json
baostock-0.7.5.dist-info/top_level.txt
demo/__init__.py
demo/demo_A_stock_k_data.py
demo/demo_A_stock_k_data_0.6.1.py
demo/demo_Adjust_factor_data.py
demo/demo_AllStock.py
demo/demo_Corporation_Report.py
demo/demo_Corporation_Report_0.6.1.py
demo/demo_Dividend_data.py
demo/demo_Dividend_data_0.6.1.py
demo/demo_Dupont_data.py
demo/demo_Evaluation_data.py
demo/demo_Index_k_data.py
demo/demo_RealTime.py
demo/demo_TradeDates.py
demo/demo_stock_Valuation_indicator_data.py
demo/demo_stock_Valuation_indicator_data_0.6.1.py
demo/helloWorld.py
demo/helloWorld_0.6.1.py
