Metadata-Version: 2.0
Name: baostock
Version: 0.7.5
Summary: A tool for obtaining historical data of China stock market
Home-page: http://www.baostock.com
Author: baostock
Author-email: baostock@163.com
License: BSD License
Platform: all
Classifier: Development Status :: 3 - Alpha
Classifier: Environment :: Console
Classifier: License :: OSI Approved :: BSD License
Classifier: Operating System :: OS Independent
Classifier: Programming Language :: Python :: 3.5
Classifier: Programming Language :: Python :: 3.6
Classifier: Topic :: Software Development :: Libraries
Requires-Dist: pandas (>=0.18.0)
